deeplatent/__init__.py
deeplatent/_core.cpython-312-aarch64-linux-gnu.so
deeplatent/morpheme_map.json
deeplatent/preprocessing.py
deeplatent/py.typed
deeplatent/tests/__init__.py
deeplatent/tests/test_tokenizer.py
deeplatent/tokenizer.py
deeplatent_nlp-0.3.5.dist-info/METADATA
deeplatent_nlp-0.3.5.dist-info/WHEEL
suhail/__init__.py
deeplatent_nlp-0.3.5.dist-info/RECORD
