Metadata-Version: 2.4
Name: deeplatent-nlp
Version: 0.3.5
Classifier: Development Status :: 4 - Beta
Classifier: Intended Audience :: Developers
Classifier: Intended Audience :: Science/Research
Classifier: License :: Other/Proprietary License
Classifier: Operating System :: OS Independent
Classifier: Programming Language :: Python :: 3
Classifier: Programming Language :: Python :: 3.8
Classifier: Programming Language :: Python :: 3.9
Classifier: Programming Language :: Python :: 3.10
Classifier: Programming Language :: Python :: 3.11
Classifier: Programming Language :: Python :: 3.12
Classifier: Programming Language :: Python :: 3.13
Classifier: Programming Language :: Rust
Classifier: Topic :: Scientific/Engineering :: Artificial Intelligence
Classifier: Topic :: Text Processing :: Linguistic
Requires-Dist: pyarrow>=17.0.0
Requires-Dist: regex>=2024.11.6
Requires-Dist: tokenizers>=0.20.3
Requires-Dist: zstandard>=0.23.0
Requires-Dist: transformers>=4.0.0 ; extra == 'all'
Requires-Dist: huggingface-hub>=0.14.0 ; extra == 'all'
Requires-Dist: zstandard>=0.21.0 ; extra == 'all'
Requires-Dist: pytest>=7.0.0 ; extra == 'dev'
Requires-Dist: pytest-cov>=4.0.0 ; extra == 'dev'
Requires-Dist: black>=23.0.0 ; extra == 'dev'
Requires-Dist: isort>=5.0.0 ; extra == 'dev'
Requires-Dist: mypy>=1.0.0 ; extra == 'dev'
Requires-Dist: zstandard>=0.21.0 ; extra == 'dev'
Requires-Dist: sphinx>=6.0.0 ; extra == 'docs'
Requires-Dist: sphinx-rtd-theme>=1.0.0 ; extra == 'docs'
Requires-Dist: transformers>=4.0.0 ; extra == 'hf'
Requires-Dist: huggingface-hub>=0.14.0 ; extra == 'hf'
Requires-Dist: zstandard>=0.21.0 ; extra == 'prepare'
Provides-Extra: all
Provides-Extra: dev
Provides-Extra: docs
Provides-Extra: hf
Provides-Extra: prepare
Summary: DeepLatent - Morphology-aware tokenizer for Arabic/English bilingual text with native Rust core
Keywords: tokenizer,arabic,nlp,morphology,sarf,deeplatent,bpe,myte,transformers,huggingface,bilingual,rust
Author-email: Mohammed Almaghrabi <almaghrabima@gmail.com>
Maintainer-email: Mohammed Almaghrabi <almaghrabima@gmail.com>
License: CC-BY-NC-4.0
Requires-Python: >=3.8
Project-URL: Bug Tracker, https://github.com/almaghrabima/deeplatent/issues
Project-URL: Documentation, https://huggingface.co/almaghrabima/deeplatent-tokenizer
Project-URL: Homepage, https://github.com/almaghrabima/deeplatent
Project-URL: HuggingFace, https://huggingface.co/almaghrabima/deeplatent-tokenizer
Project-URL: Repository, https://github.com/almaghrabima/deeplatent
